{
  "updated_at": "2026-04-19 01:51 UTC",
  "ai_summary": true,
  "sources": [
    {
      "id": "back2gaming",
      "name": "Back2Gaming",
      "region": "sea",
      "flag": "🌏",
      "regionLabel": "SEA Wide",
      "articles": [
        {
          "title": "COLORFUL iGame X870E VULCAN OC V14 AM5 Motherboard Review",
          "title_ko": "COLORFUL iGame X870E VULCAN OC V14 AM5 메인보드 리뷰",
          "link": "https://www.back2gaming.com/review/colorful-igame-x870e-vulcan-oc-v14/",
          "date": "Apr 18, 2026",
          "thumbnail": "",
          "summary_ko": "이 메인보드는 Smart Screen, 세 개의 Gen5 M.2 슬롯, LN2 모드 스위치를 갖추고 있습니다.\n강력한 18+2+2 페이즈, 110A Dr. MOS 전원 공급 장치를 제공합니다.\nPCIe 5.0 x4 M.2 슬롯 3개, 5GbE, Wi-Fi 7, USB4 40Gbps Type-C를 지원합니다."
        },
        {
          "title": "ASUS Introduces the TUF Gaming B850I WiFi Neo Mini-ITX AM5 Motherboard",
          "title_ko": "ASUS TUF Gaming B850I WiFi Neo Mini-ITX AM5 메인보드 출시",
          "link": "https://www.back2gaming.com/news/asus-introduces-the-tuf-gaming-b850i-wifi-neo-mini-itx-am5-motherboard/",
          "date": "Apr 17, 2026",
          "thumbnail": "",
          "summary_ko": "ASUS가 TUF Gaming 브랜드 최초의 Mini-ITX 폼팩터 메인보드를 선보입니다.\n이 메인보드는 AMD B850 칩셋과 AM5 플랫폼을 기반으로 Ryzen 7000, 8000, 9000 시리즈 프로세서를 지원합니다.\n최대 128GB DDR5 메모리와 PCIe 5.0 그래픽 카드 슬롯을 갖추고 있으며, 안정적인 전원 공급과 다양한 연결성을 제공합니다."
        },
        {
          "title": "GeForce Garage Teams Up With WWE to Build Tyrese Haliburton a Custom SmackDown Ring PC",
          "title_ko": "GeForce Garage, WWE와 협력하여 Tyrese Haliburton 맞춤형 SmackDown Ring PC 제작",
          "link": "https://www.back2gaming.com/news/geforce-garage-teams-up-with-wwe-to-build-tyrese-haliburton-a-custom-smackdown-ring-pc/",
          "date": "Apr 17, 2026",
          "thumbnail": "https://www.youtube.com/embed/crcGImRf-pM",
          "summary_ko": "NVIDIA, WWE, NBA 올스타 Tyrese Haliburton이 협력하여 특별한 PC를 제작했습니다.\nPC는 실제 레슬링 링 디자인을 기반으로 제작되었으며, SmackDown 브랜딩과 Haliburton의 시그니처 색상이 적용되었습니다.\n내부 하드웨어는 투명한 링 매트 아래에 전시되며, NVIDIA GeForce RTX 5080과 AMD Ryzen 7 9800X3D를 탑재했습니다."
        }
      ],
      "error": false
    },
    {
      "id": "geekculture",
      "name": "Geek Culture",
      "region": "sea",
      "flag": "🌏",
      "regionLabel": "SEA Wide",
      "articles": [
        {
          "title": "‘Metro 2039’ Marks Darker Return To The Underground, Moves On From Artyom’s Story",
          "title_ko": "메트로 2039, 지하 세계로의 어두운 귀환",
          "link": "https://geekculture.co/metro-2039-marks-darker-return-to-the-underground-moves-on-from-artyoms-story/",
          "date": "Apr 17, 2026",
          "thumbnail": "https://geekculture.co/wp-content/uploads/2026/04/metro-2039-1.jpg",
          "summary_ko": "새로운 주인공 '스트레인저'가 등장하며 이야기가 펼쳐집니다.\n게임은 이전보다 훨씬 어두운 분위기를 예고하고 있습니다.\n우크라이나의 시각을 반영한 독특한 메시지를 담고 있습니다."
        },
        {
          "title": "‘Absolute Batman’ Rises With Gaming Debut In ‘Lego Batman: Legacy of the Dark Knight’",
          "title_ko": "절대적인 배트맨, '레고 배트맨: 다크 나이트의 유산'으로 게임 데뷔",
          "link": "https://geekculture.co/absolute-batman-rises-with-gaming-debut-in-lego-batman-legacy-of-the-dark-knight/",
          "date": "Apr 16, 2026",
          "thumbnail": "https://geekculture.co/wp-content/uploads/2026/04/absolute-batman-lego-2.jpg",
          "summary_ko": "새로운 잠금 해제 가능한 슈트인 '앱솔루트 배트맨'이 공개되었습니다.\n이 슈트는 스콧 스나이더가 만든 2024년 DC 코믹스의 대체 우주 영웅입니다.\n게임은 탐험할 광활한 레고 고담 시티를 약속합니다."
        },
        {
          "title": "Insomniac’s ‘Marvel’s Spider-Man 3’ Hinted At By Peter Parker Face Model",
          "title_ko": "인섬니악의 '마블 스파이더맨 3' 힌트, 피터 파커 얼굴 모델이 암시",
          "link": "https://geekculture.co/insomniacs-marvels-spider-man-3-hinted-at-by-peter-parker-face-model/",
          "date": "Apr 15, 2026",
          "thumbnail": "https://geekculture.co/wp-content/uploads/2026/04/marvels-spiderman-3-tease-1.jpg",
          "summary_ko": "피터 파커의 얼굴 모델인 벤 조던이 '마블 스파이더맨 3'의 존재를 암시했습니다.\n그는 소셜 미디어에 얼굴 캡처 작업을 하는 사진과 함께 스파이더맨 이모티콘을 게시했습니다.\n이것이 속편인지, 아니면 다른 스파이더맨 관련 프로젝트인지에 대한 추측이 있습니다."
        }
      ],
      "error": false
    },
    {
      "id": "gamingonphone",
      "name": "GamingonPhone",
      "region": "sea",
      "flag": "🌏",
      "regionLabel": "SEA Wide",
      "articles": [
        {
          "title": "StarSavior Review: A Idle journey in a turn based Cosmos",
          "title_ko": "스타세이비어 리뷰: 턴제 우주에서의 방치형 여정",
          "link": "https://gamingonphone.com/reviews/starsavior-game-review/",
          "date": "Apr 19, 2026",
          "thumbnail": "",
          "summary_ko": "이 게임은 CounterSide 개발사인 Studio Bside의 최신 RPG로, 우주를 가로지르며 스타세이비어의 힘을 계승하는 이야기입니다.\n전투는 Honkai Star Rail과 Outerplanes와 유사한 턴제 방식이지만, PvP에 초점을 맞춘 전략성이 강조되었습니다.\n자원 수집은 AFK Journey와 Eversoul처럼 방치형 플레이를 통해 이루어지며, 일일 스태미나 제한이 있습니다."
        },
        {
          "title": "Clans of London Beginners Guide and Tricks",
          "title_ko": "Clans of London 초보자 가이드 및 팁",
          "link": "https://gamingonphone.com/guides/clans-of-london-beginners-guide-and-tricks/",
          "date": "Apr 18, 2026",
          "thumbnail": "",
          "summary_ko": "Clans of London은 5분간의 짧고 강렬한 PvP 전투에 집중하는 모바일 수집형 카드 게임입니다.\n게임의 핵심은 'Prince of London'이라는 중앙 보드 위치를 차지하는 킹 오브 더 힐 방식의 7라운드 전투입니다.\n각 클랜은 고유한 메커니즘과 승리 조건을 가지고 있으며, 플레이어는 자신의 스타일에 맞는 클랜을 선택해야 합니다."
        },
        {
          "title": "Brawl Stars April 2026 Brawl Talk: Three New Brawlers, Adidas Collab, Game Modes, Bling Rework, Skins, Buffies, and more",
          "title_ko": "Brawl Stars 2026년 4월 브롤 토크: 신규 브롤러 3명, 아디다스 콜라보, 게임 모드, 블링 개편 등",
          "link": "https://gamingonphone.com/news/brawl-stars-april-2026-brawl-talk-three-new-brawlers-collabs-game-modes-bling-rework-skins-buffies-and-more/",
          "date": "Apr 18, 2026",
          "thumbnail": "",
          "summary_ko": "이번 업데이트에서는 Damian, Starr Nova, Bolt 세 명의 신규 브롤러가 4월부터 6월까지 순차적으로 출시됩니다.\n아디다스 콜라보를 포함한 새로운 게임 모드와 이벤트, 그리고 블링 시스템 개편 및 신규 상점인 Oddities Shop이 추가됩니다.\n새로운 브롤러들은 각기 독특한 메커니즘과 능력을 가지고 있으며, Damian은 4월 24일에 출시될 예정입니다."
        }
      ],
      "error": false
    },
    {
      "id": "lowyat",
      "name": "Lowyat.net",
      "region": "sea",
      "flag": "🌏",
      "regionLabel": "SEA Wide / Malaysia",
      "articles": [
        {
          "title": "AMD Rumoured To Revive Ryzen 7 5800X3D For AM4 10th Anniversary",
          "title_ko": "AMD, 라이젠 7 5800X3D 재출시 루머",
          "link": "https://www.lowyat.net/2026/390140/amd-rumoured-to-revive-ryzen-7-5800x3d-for-am4-10th-anniversary/",
          "date": "Apr 18, 2026",
          "thumbnail": "https://www.lowyat.net/wp-content/uploads/2022/04/AMD-Ryzen-7-5800X3D-3.jpg",
          "summary_ko": "AMD가 AM4 10주년 기념으로 라이젠 7 5800X3D를 한정판으로 재출시할 것으로 알려졌습니다.\n이 CPU는 96MB의 3D V-Cache를 탑재하여 게이밍 성능이 뛰어났던 것으로 평가받습니다.\n이번 재출시는 DDR4 RAM의 가격 경쟁력과 AM4 플랫폼의 지속적인 인기에 힘입은 것으로 보입니다."
        },
        {
          "title": "Govt To Review EV Assembly Conditions Amid BYD CKD Uncertainty",
          "title_ko": "말레이시아 정부, BYD CKD 불확실성 속 EV 조립 조건 검토",
          "link": "https://www.lowyat.net/2026/390137/govt-to-review-ev-assembly-conditions-amid-byd-ckd-uncertainty/",
          "date": "Apr 18, 2026",
          "thumbnail": "https://www.lowyat.net/wp-content/uploads/2024/12/Pahang-EV-assembly-manufacturing-1.jpg",
          "summary_ko": "말레이시아 정부는 전기차(EV) 기업의 현지 조립 조건이 지나치게 제한적이라는 우려에 따라 이를 재검토할 예정입니다.\nBYD가 CKD 조립 시설 설립 계획을 재고하고 있다는 보도 속에 이번 검토가 이루어지게 되었습니다.\nMITI는 BYD뿐만 아니라 모든 신규 진입 EV 기업에 CKD 정책이 적용된다고 밝혔습니다."
        },
        {
          "title": "Activision Announces Call Of Duty Movie; Developing With Paramount",
          "title_ko": "Activision, 콜 오브 듀티 영화 제작 발표; 파라마운트와 개발 중",
          "link": "https://www.lowyat.net/2026/390129/activision-call-of-duty-movie-paramount/",
          "date": "Apr 18, 2026",
          "thumbnail": "https://www.lowyat.net/wp-content/uploads/2026/04/Call-of-Duty-movie-Paramount.webp",
          "summary_ko": "Activision이 인기 게임 시리즈인 콜 오브 듀티의 영화 제작을 공식 발표했습니다.\n영화는 피터 버그가 감독 및 공동 각본을 맡고, 파라마운트가 배급 및 제작에 참여합니다.\n영화의 배경 설정은 아직 공개되지 않았으며, 시리즈의 다양한 시대적 배경을 활용할 가능성이 있습니다."
        }
      ],
      "error": false
    },
    {
      "id": "gamingph",
      "name": "GamingPH",
      "region": "ph",
      "flag": "🇵🇭",
      "regionLabel": "Philippines",
      "articles": [
        {
          "title": "Jollibee Officially Heads to Mobile Legends: Bang Bang as Battle Emote",
          "title_ko": "졸리비, 모바일 레전드: 뱅뱅 배틀 이모트로 공식 등장",
          "link": "https://gamingph.com/2026/04/jollibee-officially-heads-to-mobile-legends-bang-bang-as-battle-emote/",
          "date": "Apr 18, 2026",
          "thumbnail": "https://i0.wp.com/gamingph.com/wp-content/uploads/2026/04/image-16.png?resize=950%2C912&#038;ssl=1",
          "summary_ko": "졸리비가 모바일 레전드: 뱅뱅의 새로운 인게임 배틀 이모트로 등장합니다.\n필리핀의 유명 마스코트가 게임에 추가되어 팬들의 관심을 받고 있습니다.\n4월 22일부터 5월 20일까지 게임 접속 시 WOW BIDA 배틀 이모트를 획득할 수 있습니다."
        },
        {
          "title": "It Didn’t Take Long for Pragmata to Get a CJ Mod",
          "title_ko": "Pragmata, CJ 모드 등장까지 오래 걸리지 않았다",
          "link": "https://gamingph.com/2026/04/it-didnt-take-long-for-pragmata-to-get-a-cj-mod/",
          "date": "Apr 18, 2026",
          "thumbnail": "https://i0.wp.com/gamingph.com/wp-content/uploads/2026/04/image-14.png?resize=950%2C534&#038;ssl=1",
          "summary_ko": "Pragmata 게임에 Grand Theft Auto: San Andreas의 Carl Johnson으로 대체하는 모드가 등장했습니다.\n이 모드는 Nexus Mods에 \"CJ (GTA San Andreas Definitive Edition)\"라는 제목으로 올라왔습니다.\n모드를 사용하려면 REFramework가 필요하며, Nexus Mods 페이지에서 다운로드할 수 있습니다."
        },
        {
          "title": "Nubia Neo 5 GT 5G Review – MediaTek Octa-Core Power Meets Active Cooling",
          "title_ko": "Nubia Neo 5 GT 5G 리뷰 – 미디어텍 옥타코어 성능과 액티브 쿨링의 만남",
          "link": "https://gamingph.com/2026/04/nubia-neo-5-gt-5g-review-mediatek-power-meets-active-cooling/",
          "date": "Apr 14, 2026",
          "thumbnail": "https://i0.wp.com/gamingph.com/wp-content/uploads/2026/04/nubia-neo-5-gt-5g-box-with-phone-and-bud.jpg?resize=950%2C534&#038;ssl=1",
          "summary_ko": "nubia Neo 5 GT 5G는 경쟁력 있는 가격으로 게이머들이 원하는 성능을 제공합니다.\n이 스마트폰은 칩셋 성능뿐만 아니라 내장된 액티브 쿨링 팬으로 발열 관리를 강화했습니다.\n전용 성능 모드는 CPU와 GPU를 더욱 적극적으로 활용하여 고사양 게임 플레이를 지원합니다."
        }
      ],
      "error": false
    },
    {
      "id": "gamelade",
      "name": "Gamelade",
      "region": "vn",
      "flag": "🇻🇳",
      "regionLabel": "Vietnam",
      "articles": [
        {
          "title": "What the Clash? bổ sung chế độ multiplayer",
          "title_ko": "What the Clash? 멀티플레이어 모드 추가",
          "link": "https://gamelade.vn/what-the-clash-bo-sung-che-do-multiplayer/",
          "date": "Apr 18, 2026",
          "thumbnail": "https://gamelade1.sgp1.cdn.digitaloceanspaces.com/wp-content/uploads/2026/04/i-1.webp",
          "summary_ko": "What the Clash?에 새로운 멀티플레이어 모드가 추가되었습니다.\n이제 같은 기기에서 친구와 1v1 대결을 즐길 수 있습니다.\nApple TV와 Mac에서도 분할 화면 모드를 지원합니다."
        },
        {
          "title": "Gears Tower Defense chính thức ra mắt",
          "title_ko": "Gears Tower Defense 공식 출시",
          "link": "https://gamelade.vn/gears-tower-defense-chinh-thuc-ra-mat/",
          "date": "Apr 18, 2026",
          "thumbnail": "https://gamelade1.sgp1.cdn.digitaloceanspaces.com/wp-content/uploads/2026/04/r-2.jpg",
          "summary_ko": "Gears Tower Defense가 iOS 및 Android에서 정식 출시되었습니다.\n22세기, 통제 불능 AI로 인해 지하로 숨어든 인류의 이야기를 다룹니다.\n기존 타워 디펜스 방식에 영웅 병합 등 새로운 메커니즘을 추가했습니다."
        },
        {
          "title": "SNK công bố ngày ra mắt nhân vật Wolfgang Krauser cho Fatal Fury: City of the Wolves",
          "title_ko": "SNK, Fatal Fury: City of the Wolves의 볼프강 크라우저 캐릭터 출시일 공개",
          "link": "https://gamelade.vn/snk-cong-bo-ngay-ra-mat-nhan-vat-wolfgang-krauser-cho-fatal-fury-city-of-the-wolves/",
          "date": "Apr 18, 2026",
          "thumbnail": "https://gamelade1.sgp1.cdn.digitaloceanspaces.com/wp-content/uploads/2026/04/fatal-fury-city-of-the-wolves-wolfgang-krauser_jpg_1200x0_crop_q85.webp",
          "summary_ko": "볼프강 크라우저 DLC 캐릭터가 4월 24일에 Fatal Fury: City of the Wolves에 추가됩니다.\n그는 어둠의 황제로서 지하 세계를 지배했으나, 아들의 대회 개최로 다시 등장합니다.\n캐릭터 출시와 함께 게임 출시 1주년을 기념하는 대규모 업데이트가 진행됩니다."
        }
      ],
      "error": false
    },
    {
      "id": "droidsans",
      "name": "Droidsans",
      "region": "th",
      "flag": "🇹🇭",
      "regionLabel": "Thailand",
      "articles": [
        {
          "title": "ญี่ปุ่นทุ่มงบ 6 หมื่นล้านเยน ดัน Sony สร้างโรงงานเซนเซอร์ภาพ AI ที่คุมาโมโตะ เสริมแกร่งยุครถยนต์ไร้คนขับ",
          "title_ko": "ญี่ปุ่นทุ่มงบ 6 หมื่นล้านเยน ดัน Sony สร้างโรงงานเซนเซอร์ภาพ AI ที่คุมาโมโตะ เสริมแกร่งยุครถยนต์ไร้คนขับ",
          "link": "https://droidsans.com/japan-financial-support-for-sony/",
          "date": "Apr 18, 2026",
          "thumbnail": "",
          "summary_ko": "ญี่ปุ่นทุ่มงบ 6 หมื่นล้านเยน สนับสนุน Sony สร้างโรงงานเซนเซอร์ภาพ AI ที่คุมาโมโตะ\nโรงงานแห่งนี้จะเสริมความแข็งแกร่งให้กับ Sony ในยุครถยนต์ไร้คนขับ\nคาดว่าโรงงานจะผลิตเซนเซอร์ภาพสำหรับรถยนต์ไร้คนขับโดยเฉพาะ"
        },
        {
          "title": "Insta360 Luna กล้องกิมบอลเลนส์คู่รุ่นใหม่ ได้ฟีเจอร์ระดับเทพจาก Leica ลุ้นเข้าไทย พ.ค.นี้",
          "title_ko": "Insta360 Luna กล้องกิมบอลเลนส์คู่รุ่นใหม่ ได้ฟีเจอร์ระดับเทพจาก Leica ลุ้นเข้าไทย พ.ค.นี้",
          "link": "https://droidsans.com/insta360-luna-leak/",
          "date": "Apr 18, 2026",
          "thumbnail": "",
          "summary_ko": "Insta360 Luna กล้องกิมบอลเลนส์คู่รุ่นใหม่ มาพร้อมฟีเจอร์ระดับเทพจาก Leica\nกล้องรุ่นนี้มีดีไซน์เลนส์คู่ และคาดว่าจะเข้าไทยในเดือนพฤษภาคมนี้\nมีฟีเจอร์ถ่ายภาพบุคคลที่สวยงาม และการควบคุมที่ง่ายดาย"
        },
        {
          "title": "ข้อมูลใหม่ iPhone 18 Pro เผยสีใหม่ มี Dark Cherry และอื่นๆ อีก 3 สี",
          "title_ko": "ข้อมูลใหม่ iPhone 18 Pro เผยสีใหม่ มี Dark Cherry และอื่นๆ อีก 3 สี",
          "link": "https://droidsans.com/iphone-18-pro-dark-cherry/",
          "date": "Apr 18, 2026",
          "thumbnail": "",
          "summary_ko": "iPhone 18 Pro รุ่นใหม่จะมาพร้อมสีใหม่ Dark Cherry และอีก 3 สี\nสีใหม่เหล่านี้จะเพิ่มทางเลือกให้กับผู้ใช้งาน iPhone\nคาดว่า iPhone 18 Pro จะเปิดตัวในปี 2026 พร้อมสีใหม่ที่น่าสนใจ"
        }
      ],
      "error": false
    },
    {
      "id": "gamebrott",
      "name": "Gamebrott",
      "region": "id",
      "flag": "🇮🇩",
      "regionLabel": "Indonesia",
      "articles": [
        {
          "title": "Player Resident Evil Requiem Rata-rata Telah Menamatkan Game Ini di PS5 dan PC",
          "title_ko": "플레이어 Resident Evil Requiem 평균적으로 이 게임을 PS5와 PC에서 완료했습니다",
          "link": "https://gamebrott.com/player-resident-evil-requiem-tamatkan-game-ps5-pc/",
          "date": "Apr 19, 2026",
          "thumbnail": "",
          "summary_ko": "Resident Evil 영화 감독 Zach Cregger는 자신의 영화가 게임과 같은 분위기를 가질 것이라고 말했습니다.\n그는 영화가 게임의 분위기와 유사할 것이라고 설명했습니다.\n이것은 팬들에게 흥미로운 소식입니다."
        },
        {
          "title": "Internet Lemot, 5 Rekomendasi Router Wi-Fi Ini Bikin Internet Lebih Stabil",
          "title_ko": "느린 인터넷, 인터넷을 더 안정적으로 만드는 5가지 Wi-Fi 라우터 추천",
          "link": "https://gamebrott.com/rekomendasi-router-wi-fi/",
          "date": "Apr 18, 2026",
          "thumbnail": "",
          "summary_ko": "Umamusume Pretty Derby의 Epithet Trackblazer 목록입니다!\n이 기사에서는 Umamusume Pretty Derby의 Epithet Trackblazer 목록을 공유할 것입니다."
        },
        {
          "title": "Daftar Epithet Trackblazer Umamusume Pretty Derby!",
          "title_ko": "Umamusume Pretty Derby의 Epithet Trackblazer 목록!",
          "link": "https://gamebrott.com/daftar-epithet-trackblazer-umamusume-pretty-derby/",
          "date": "Apr 18, 2026",
          "thumbnail": "",
          "summary_ko": "Umamusume Pretty Derby의 Champions Meeting Aquarius Cup 가이드입니다.\n이 기사에서는 Umamusume Pretty Derby의 Champions Meeting Aquarius Cup 가이드를 공유할 것입니다."
        }
      ],
      "error": false
    },
    {
      "id": "kakuchopurei",
      "name": "Kakuchopurei",
      "region": "my",
      "flag": "🇲🇾",
      "regionLabel": "Malaysia",
      "articles": [
        {
          "title": "Samsung S26 Ultra Review: Incremental Improvements With Meaningful Upgrades",
          "title_ko": "삼성 S26 Ultra 리뷰: 의미 있는 업그레이드를 갖춘 점진적인 개선",
          "link": "https://www.kakuchopurei.com/2026/04/samsung-s26-ultra-review-kkp/",
          "date": "Apr 17, 2026",
          "thumbnail": "https://www.kakuchopurei.com/wp-content/uploads/2026/04/IMG_7741-1-scaled.jpg",
          "summary_ko": "삼성 S26 Ultra는 전반적으로 훌륭한 스마트폰이지만, 몇 가지 의문스러운 결정이 있습니다.\n티타늄에서 알루미늄으로 회귀한 것은 퇴보처럼 느껴지며, S펜은 블루투스 기능이 여전히 부족합니다.\n배터리 용량은 그대로지만, 실제 사용 시 배터리 수명은 작년 모델보다 크게 향상되었습니다."
        },
        {
          "title": "Is The Amazing Digital Circus Heading To Malaysian Theatres?",
          "title_ko": "말레이시아 극장에서 The Amazing Digital Circus를 볼 수 있을까?",
          "link": "https://www.kakuchopurei.com/2026/04/the-amazing-digital-circus-finale-screening-in-malaysia-theatres/",
          "date": "Apr 15, 2026",
          "thumbnail": "",
          "summary_ko": "인기 유튜브 애니메이션 시리즈 The Amazing Digital Circus가 전 세계 극장 개봉을 계획하고 있습니다.\n말레이시아 팬들은 현지 극장에서 상영을 요청하는 바이럴 소셜 미디어 캠페인을 시작했습니다.\n팬들의 뜨거운 관심과 요청으로 말레이시아 극장 개봉 가능성이 높아지고 있습니다."
        },
        {
          "title": "MOUSE: P.I. For Hire Review – Fine Cheese Noir",
          "title_ko": "MOUSE: P.I. For Hire 리뷰 – 훌륭한 치즈 느와르",
          "link": "https://www.kakuchopurei.com/2026/04/mouse-p-i-for-hire-review-kkp/",
          "date": "Apr 14, 2026",
          "thumbnail": "https://www.kakuchopurei.com/wp-content/uploads/2026/04/mousePI_04.jpg",
          "summary_ko": "인디 스튜디오 Fumi Games가 1930년대 고무 호스 애니메이션 스타일의 흑백 그래픽으로 독특한 느와르 FPS 게임을 선보입니다.\n플레이어는 탐정 Jack Pepper가 되어 Mouseburg의 범죄와 음모를 파헤치며 총격전을 벌입니다.\n컵헤드 이후로 이와 같은 고무 호스 애니메이션 기법을 성공적으로 구현한 게임으로 평가받습니다."
        }
      ],
      "error": false
    }
  ]
}